snake/__init__.py
snake/activations.py
torch_snake-1.0.1.dist-info/LICENSE
torch_snake-1.0.1.dist-info/METADATA
torch_snake-1.0.1.dist-info/WHEEL
torch_snake-1.0.1.dist-info/top_level.txt
torch_snake-1.0.1.dist-info/RECORD
