Metadata-Version: 2.1
Name: torch-snake
Version: 1.0.1
Summary: Sample PyTorch implementation of the snake activation function
Home-page: https://github.com/EdwardDixon/snake
Author: Edward Dixon
Author-email: dixon.edward@gmail.com
Classifier: Programming Language :: Python :: 3
Classifier: License :: OSI Approved :: MIT License
Classifier: Operating System :: OS Independent
Requires-Python: >=3.6
License-File: LICENSE
Requires-Dist: torch
